[
  {
    "file": "about.md",
    "title": "概要"
  },
  {
    "file": "install.md",
    "title": "インストール"
  },
  {
    "file": "names.md",
    "title": "各部名称"
  },
  {
    "file": "processtype.md",
    "title": "加工種類"
  },
  {
    "file": "parameter.md",
    "title": "パラメータ設定"
  },
  {
    "file": "usersetting.md",
    "title": "ユーザ設定"
  },
  {
    "file": "flow.md",
    "title": "使い方"
  },
  {
    "file": "griditem.md",
    "title": "グリッドアイテムの活用"
  },
  {
    "file": "userorigin.md",
    "title": "ユーザ原点の利用方法"
  },
  {
    "file": "userdictionary.md",
    "title": "ユーザ辞書"
  },
  {
    "_file": "releasenote.md",
    "_title": "リリースノート"
  }
]
